.gitignore
CMakeLists.txt
LICENSE
README.rst
pyproject.toml
setup.py
.github/environment.yml
.github/workflows/build.yml
pdal/filters/PythonFilter.cpp
pdal/filters/PythonFilter.hpp
pdal/io/NumpyReader.cpp
pdal/io/NumpyReader.hpp
pdal/nlohmann/json.hpp
pdal/plang/Environment.cpp
pdal/plang/Environment.hpp
pdal/plang/Invocation.cpp
pdal/plang/Invocation.hpp
pdal/plang/Redirector.cpp
pdal/plang/Redirector.hpp
pdal/plang/Script.cpp
pdal/plang/Script.hpp
pdal/plang/gil.hpp
pdal/test/NumpyReaderTest.cpp
pdal/test/PythonFilterTest.cpp
pdal/test/Support.cpp
pdal/test/Support.hpp
pdal/test/TestConfig.hpp
pdal/test/data/1.2-with-color.las
pdal/test/data/1.2-with-color.npy
pdal/test/data/autzen-utm.las
pdal/test/data/autzen.las
pdal/test/data/four-floats-be.bin
pdal/test/data/four-floats.py
pdal/test/data/perlin.npy
pdal/test/data/test1.py
pdal/test/data/threedim.npy
pdal/test/data/threedim.py
pdal/test/data/twodim.npy
pdal/test/data/logs/log_py.txt
pdal/test/data/pipeline/crop_wkt_2d_classification.json
pdal/test/data/pipeline/from-module.json
pdal/test/data/pipeline/predicate-embed.json
pdal/test/data/pipeline/predicate-keep-ground-and-unclass.json
pdal/test/data/pipeline/predicate-keep-last-return.json
pdal/test/data/pipeline/predicate-keep-specified-returns.json
pdal/test/data/pipeline/programmable-update-y-dims.json
pdal/test/data/pipeline/reproject.json
pdal/test/gtest/CMakeLists.txt
pdal/test/gtest/CONTRIBUTORS
pdal/test/gtest/LICENSE
pdal/test/gtest/README.md
pdal/test/gtest/cmake/Config.cmake.in
pdal/test/gtest/cmake/gtest.pc.in
pdal/test/gtest/cmake/gtest_main.pc.in
pdal/test/gtest/cmake/internal_utils.cmake
pdal/test/gtest/cmake/libgtest.la.in
pdal/test/gtest/docs/advanced.md
pdal/test/gtest/docs/faq.md
pdal/test/gtest/docs/pkgconfig.md
pdal/test/gtest/docs/primer.md
pdal/test/gtest/docs/pump_manual.md
pdal/test/gtest/docs/samples.md
pdal/test/gtest/include/gtest/gtest-death-test.h
pdal/test/gtest/include/gtest/gtest-matchers.h
pdal_plugins.egg-info/PKG-INFO
pdal_plugins.egg-info/SOURCES.txt
pdal_plugins.egg-info/dependency_links.txt
pdal_plugins.egg-info/top_level.txt